alphabet_sorter/__init__.py
alphabet_sorter/sorting.py
tests/__init__.py
tests/test_sorting.py
ascending_sort-0.1.dist-info/METADATA
ascending_sort-0.1.dist-info/WHEEL
ascending_sort-0.1.dist-info/top_level.txt
ascending_sort-0.1.dist-info/RECORD
